{
  "id": "cache_20260205_130127_beb6c941",
  "physical_time": "2026-02-05T13:01:27.853525",
  "activity_type": "知识图谱整理-关系生成（从合并转换）",
  "filename": "cache_20260205_130127_beb6c941.md",
  "text": "实体1:\n- name: 叶文洁（地球三体叛军邮件列表）\n- content: 地球三体叛军是一个全球性的叛乱组织,由社会名流和各领域精英组成,成员包括科学家、文学家、政治家等。该组织最初由叶文洁担任最高统帅,但她仅为精神领袖,不参与组织的具体运作,对组织发展情况了解有限。组织的目标是推翻人类暴政并与三体文明建立联系,成员共同的口号是“世界属于三体！”。组织内部存在派系斗争,例如全球起义派和清除异己派,各派在发展方向和行动策略上存在分歧。该组织拥有一定的军事力量和威胁能力,试图利用武器威胁人类以达成目的,并曾计划制造环境灾难等激进行动。他们通过特定方式招募成员,并定期聚会讨论重要议题。该组织的目标是“失去一切”,放弃人类文明,其具体目的尚不明确,但旨在引导特定人员参与活动。由于其对人类的威胁,该组织正面临各国政府的搜捕。\n- memory_cache: ## 记忆缓存 - 更新\n\n**1. 当前摘要**\n\n当前阅读的内容是关于地球三体组织的内部构成和发展情况的进一步描述。文章指出，叶文洁作为最高统帅，并不参与组织的具体运作，对组织庞大的发展过程并不了解。各国政府最初对该组织重视不足，利用政府的保守和想象力不足作为保护。随后，文章详细介绍了地球三体组织内部的两个主要派别：降临派和拯救派。降临派是组织最原始的形态，由伊文斯物种共产主义的信奉者组成，他们对人类文明彻底绝望，并以对人类的仇恨为驱动力。拯救派则是一个宗教团体，由三体教的教徒组成。文章还强调，高级知识阶层对外星文明具有天然的吸引力，并容易产生美好的幻想，这使得地球三体组织能够吸引更多成员。\n\n*   **叶文洁的角色：** 叶文洁仅为精神领袖，不参与组织具体运作，暗示组织内部存在复杂的权力结构和自主发展能力。\n*   **政府反应：** 政府最初对地球三体组织重视不足，利用其保守和想象力不足进行自我保护，直到组织发展武装力量才引起重视。\n*   **组织内部派别：** 地球三体组织分为降临派和拯救派两大派别，各自有不同的理念和目标。\n*   **降临派：** 降临派对人类文明彻底绝望，以仇恨为驱动力，其座右铭是“我们不知道外星文明是什么样子，但知道人类”。\n*   **拯救派：** 拯救派本质上是宗教团体，由三体教教徒组成，对外星文明抱有美好的幻想。\n*   **高级知识阶层：** 高级知识阶层对外星文明具有天然的吸引力，容易受到诱惑，成为组织成员。\n\n**2. 自我思考**\n\n*   **关注内容：**\n    *   降临派和拯救派的具体区别是什么？他们的理念和目标是否存在冲突？\n    *   伊文斯物种共产主义的信奉者是如何形成的？他们的思想根源是什么？\n    *   三体教的教徒是如何产生的？他们对三体文明的信仰是什么？\n    *   高级知识阶层为何对外星文明抱有如此美好的幻想？这种幻想是否会成为他们的弱点？\n    *   地球三体组织内部的权力结构是如何运作的？叶文洁在其中扮演什么角色？\n*   **预判重点：**\n    *   降临派和拯救派之间的矛盾可能会激化，导致组织内部的分裂。\n    *   伊文斯物种共产主义的思想可能会对人类文明产生深远的影响。\n    *   三体教的信仰可能会成为组织成员的坚定动力，但也可能导致他们走向极端。\n    *   高级知识阶层对外星文明的幻想可能会被三体文明利用，从而达到其目的。\n    *   叶文洁可能会在组织内部发挥关键作用，她的选择将影响故事的走向。\n*   **疑虑/注意：**\n    *   降临派对人类的绝望和仇恨是否会让他们采取极端的行动？\n    *   拯救派对三体文明的信仰是否会蒙蔽他们的双眼？\n    *   地球三体组织是否会利用高级知识阶层的幻想来控制他们？\n    *   政府对地球三体组织的重视不足是否会给人类文明带来灾难？\n\n**3. 系统状态**\n\n*   **文档名：** 三体1疯狂年代.txt\n*   **已处理文本范围：** 处理到“现在她”结束。\n\n实体2:\n- name: 叶文洁\n- content: 叶文洁是一位六十岁左右的已退休清华大学物理系天体物理专业教授、国家科学院院士。她在“文革”期间曾就职于红岸基地,负责接收和发送来自三体世界的信息,并在发射部和监听部工作。她对科学复兴的态度较为质疑,并对红岸工程的真实性以及参与的谋杀事件（包括1979年10月21日杀害雷志成和杨卫宁）产生怀疑。作为地球三体组织的重要成员和最高统帅、精神领袖,她启动发射系统向三体文明发送信息,并试图破坏接收系统,对人类文明的未来感到绝望,但承认自己“点燃了火,却控制不了它”。她曾计划建立第三红岸基地,完成了接收部分的建设,但因三体世界停止发送信息而停止。晚年,她试图与当年参与谋杀其父亲的红卫兵和解,并探寻她们是否应该忏悔。她对伊文斯的“物种共产主义”理想持怀疑态度,并积极寻求阻止伊文斯种植的树林被砍伐,展现出正义感和责任感。她接受过审讯,并透露了三体文明的宇宙航行速度,解释了拯救派不攻击“审判日”号的原因,并声称自己对三体世界没有宗教感情。在审讯中,她对质子信号的细节有所了解,解释了三体文明发射质子的原因和目的,并引用了伊文斯关于质子信号导致人类科学死亡的预言,但声称自己对质子如何锁死人类科学并不知情。在得知三体文明的真相后,身体状况不佳的她坚持前往红岸基地遗址,最终在雷达峰上耗尽生命力,并在生命的最后时刻回忆起亲手结束两位军人生命的情景,凝视着红岸基地的日落。她曾被邀请前往第二红岸基地,暗示着她将在新的阶段中扮演重要角色。\n- memory_cache: ## 记忆缓存 - 更新\n\n**1. 当前摘要**\n\n新的文本描述了叶文洁在得知三体文明真相后，坚持前往红岸基地遗址的经历，以及她在遗址的所见所感。汪淼建议返回，叶文洁在众人帮助下艰难地登上了雷达峰。在峰顶，他们发现红岸基地已被彻底拆除，只剩下一片荒野。叶文洁却发现了一个巨大的金属基座，那是当年发送地球文明信息的发射天线基座。他们还在遗址找到了一块刻有“红岸基地原址”字样的石碑，石碑显得微小，仿佛是为了遗忘而存在。叶文洁来到悬崖边，回忆起当年亲手结束两位军人生命的情景，她的目光投向了远处的齐家屯。在生命的最后时刻，她希望能够再看一次红岸基地的日落。\n\n*   **核心事件：** 叶文洁一行人到达红岸基地遗址，发现基地已被拆除，叶文洁回忆起当年的往事，并在生命的最后时刻凝视着红岸基地的日落。\n*   **关键细节：**\n    *   **叶文洁的执着：** 叶文洁不顾身体状况，坚持要回到红岸基地遗址，体现了她对过去的强烈情感和对三体文明的复杂态度。\n    *   **基地的彻底拆除：** 红岸基地被彻底拆除，暗示着人类试图抹去这段历史，但叶文洁的出现打破了这种平静。\n    *   **天线基座的发现：** 天线基座是地球文明向宇宙发送信息的关键设备，它的存在证明了人类曾经试图与外星文明进行沟通。\n    *   **遗忘的石碑：** 石碑的微小尺寸和刻字内容，暗示着人类试图遗忘这段历史，但历史的痕迹仍然存在。\n    *   **叶文洁的回忆：** 叶文洁回忆起当年在悬崖边结束两位军人生命的情景，暗示了她与红岸基地和三体文明之间存在着更深层次的联系。\n*   **重要对话/描述：**\n    *   叶文洁说：“这是天线的基座。”揭示了基座的用途和重要性。\n    *   石碑上的“红岸基地原址 (1968～1987)”字样，记录了红岸基地的时间线。\n    *   “碑是那么小，与其说是为了纪念，更像是为了忘却。”这句话点明了人类试图遗忘这段历史的意图。\n\n**2. 自我思考**\n\n*   **关注内容：**\n    *   叶文洁为何如此执着于红岸基地？她当年在红岸基地究竟经历了什么？\n    *   红岸基地被拆除的真正原因是什么？是出于对三体文明的恐惧，还是为了掩盖某些真相？\n    *   叶文洁回忆起当年结束两位军人生命的情景，这与三体文明有什么关联？\n    *   齐家屯在叶文洁心中代表着什么？\n*   **预判重点：**\n    *   叶文洁的回忆可能会揭示更多关于红岸基地和三体文明的真相。\n    *   红岸基地遗址可能会隐藏着一些关键线索，帮助丁仪和汪淼了解三体文明的起源和目的。\n    *   叶文洁的死亡可能会引发新的事件，推动故事的发展。\n*   **疑虑/注意：**\n    *   叶文洁的行为是否受到三体文明的影响？她是否是三体文明的同盟者？\n    *   红岸基地拆除后，是否还有其他遗留物或秘密？\n    *   齐家屯是否与叶文洁的过去有关？\n\n**3. 系统状态**\n\n*   **文档名：** 三体1疯狂年代.txt\n*   **已处理文本范围：** 处理到“在西方的天际，正在”结束。\n",
  "document_path": ""
}