{
  "id": "cache_20260204_234147_78916cc0",
  "physical_time": "2026-02-04T23:41:47.381052",
  "activity_type": "文档处理",
  "filename": "cache_20260204_234147_78916cc0.md",
  "text": "和木星。她在三条边上分别标上距离，在地球顶点标上了两个到达时间。由木星到地球的距离很容易算出电磁辐射由木星直接到达地球消耗的时间，她接着又算出了电磁辐射由木星到达太阳，再由太阳到达地球的时间，两者相差正是十六分四十二秒！\n　　叶文洁翻出了以前自己搞出的太阳结构数学模型，试图从理论上找到一些蛛丝马迹。她的目光很快锁定在太阳辐射层中一种叫“能量镜面”的东西上。从日核反应区发出的能量开始是以高能伽马射线的形式发出，辐射区通过对这些高能粒子的吸收，再发射实现能量传递，经过无数次这种再吸引再辐射的漫长过程(一个光子脱离太阳可能需要一千年的时间)，高能伽马射线经过X射线、极紫外线、紫外线逐渐变为可见光和其他形式的辐射。这些是在太阳研究中早已明确的内容。叶文洁的数学模型产生的一个新结果是：在这些不同频率辐射的转换之间，存在着许多明显的界面，辐射区由里向外，每越过一个界面，辐射频率就明显下降一个等级，这与传统观点认为辐射区的频率是渐变的有所不同。计算表明，这种界面会将来自低频侧的辐射反射回去，于是她就想了那么一个命名。\n　　叶文洁开始仔细研究这一层层悬浮在太阳电浆海洋中的飘忽不定的薄膜，她发现，这种只能在恒星内部的高能海洋中出现的东西，有许多奇妙的性质，其中最不可思议的是它的“增益反射”特性，而这与太阳电磁辐射之谜似乎有关。但这种特性过分离奇，难以证实，叶文洁自己都难以置信，更有可能是令人目眩的复杂计算中产生的一些误导所致。\n　　现在，叶文洁初步证实了自己关于太阳能量镜面增益反射的猜想：能量镜面并非简单地反射低频侧的电磁辐射，而是将它放大了！以前观测到的那些在狭窄频段的神秘突变，其实是来自宇宙间的辐射被放大后的结果，所以在太阳表面观察不到任何相应的扰动。\n　　很可能，这一次，太阳收到木星的电磁辐射后又发射出来，只是强度增加了近亿倍！地球以十六分四十二秒的时间差分别收到了放大前后的这两次辐射",
  "document_path": "/home/linkco/exa/Temporal_Memory_Graph/data/三体1疯狂年代.txt"
}