{
  "id": "cache_20260205_020750_18e89ab7",
  "physical_time": "2026-02-05T02:07:50.853691",
  "activity_type": "文档处理",
  "filename": "cache_20260205_020750_18e89ab7.md",
  "text": "刚顺便看过了。雷达峰的顶部是一种很不寻常的地质结构，覆盖着一层厚十几米的胶泥，这种胶泥层导电性很差。接地线埋下后，接地电阻总是达不到要求；把接地电极深埋也不行，因为这种胶泥层对导线有很强的腐蚀作用，时间长了可能从中部将接地线蚀断。最后只好将接地线排从那道悬崖上垂下去，沿着崖壁一直垂到没有胶泥层的地方，将接地电极埋设在崖壁上的那个位置，即使这样接地仍然不稳定，电阻常常超标，问题都出在接地线在悬崖壁上的部分，这时维修人员就要用绳索吊下去修。那名技术员就向外围维修班打招呼，班里的一名战士在一根铁柱上系好绳索就顺着崖壁下去了，在下面折腾了半个多小时，满头大汗地上来，说找不到故障。这次监听作业眼看就要受到影响，只好上报基地指挥部。我就在悬崖顶上那个系绳索的铁柱旁等着，事情果然如我预料，雷志成跟着那名战士来了。\n　　应该说，雷志成是一名很敬业的政工干部，忠实地按照那时对他们的要求去做：与群众打一片，时时站在第一线，也许是为了做姿态，但他的确做得很好，基地急难险重的工作中都少不了他的身影，而以往他干得最多的，就是抢修接地线这个既危险又累的活。这工作虽然没有多高的技术含量，但需要经验，因为故障可能是因接地线暴露露天产生的难以察觉的接触不良，也可能是因为接地电极埋设处因干燥等原因导致的导电性差，现在负责外围维修的这批志愿兵刚刚调换过，都没有经验，所以我估计他多半要来。他系好安全带，就顺着绳索下去了，好像我不存在似的。我借口把那名战士支走了，悬崖顶上只剩下我一人，然后我从衣袋中掏出了一件东西，那是一叠短钢锯，是一条长锯条折成三段后叠在一起的，这样绳索的断口看不出是锯断的。\n　　正在这时我丈夫杨卫宁来了。\n　　问清事情的原由后，他向悬崖下看了看，说要是检查接地电极的话需要开挖，老雷一个人在下面太费劲。他要下去帮忙，于是系上那名战士留下的安全带。我说再拿一条绳索吧，他说不用，这条绳子就挺粗挺结实，",
  "document_path": "/home/linkco/exa/Temporal_Memory_Graph/data/三体1疯狂年代.txt"
}