{
  "id": "cache_20260204_093833_818be8ee",
  "physical_time": "2026-02-04T09:38:33.777747",
  "activity_type": "文档处理",
  "filename": "cache_20260204_093833_818be8ee.md",
  "text": "成的挽扶，自己艰难地走下飞机，一阵强风差点把她吹倒，风吹在仍转动的旋翼上，发出尖利的啸声。风中的森林气息文洁很熟悉，她认识这风，这风也认识她，这是大兴安岭的风。\n　　她很快听到了另一种声音，一个低沉浑厚的嗡嗡声，浑厚而有力，似乎构成了整个世界的背景，这是不远处抛物面天线在风中的声音，只有到了跟前，才能真正感受到这张天网的巨大。叶文洁的人生在这一个月里转了一个大圈又回来了——她现在是在雷达峰上。\n　　叶文洁不由得转头朝她的建设兵团连队所在的方向望去，只看到暮色中一片迷蒙的林海。\n　　直升机显然不是专为接她的，几名士兵走过来，从机舱里卸下那些军绿色的货箱，他们从她身边走过，没人看她一眼。她和雷志成、杨卫宁一行三人继续向前走去，叶文洁发现雷达峰的峰顶是这样的宽阔，在天线的下面有一小群白色建筑物，与天线相比，它们像几块精致的积木。他们正朝有两名哨兵站岗的基地大门走去，走到门前，他们停了下来。\n　　雷志成转向叶文洁，郑重地说：“叶文洁，你的反革命罪行证据确凿，将要面临的审判也是罪有应得；现在，你面前有一个立功赎罪的机会，你可以接受，也可以拒绝。”他向天线方向指了指，“这是一个国防科研基地，其中正在进行的研究项目需要你掌握的专业知识，更具体的，请杨总工程师为你介绍，你要慎重考虑。”说完他对杨卫宁点了点头，尾随搬运物资的士兵一起走进了基地。\n　　杨卫宁等别人走远了，向叶文洁示意了一下，带她走远些，显然是怕哨兵听到下面的谈话。这时，他不再隐藏自己与她的相识：“叶文洁，我可向你说清楚，这不是什么机会。我向法院军管会了解过，虽然程丽华力主重判，但具体到你的情节，刑期最多也就是十年，考虑到可能的减刑，也就是六七年的样子。而这里——”他向基地方向偏了一下头，“是最高密级的研究项目，以你的身份，走进这道门，可能……”他停了好一会儿，似乎想让天线在风中的轰鸣声加重自己的语气，“一辈子都出不来了。”\n　",
  "document_path": "/home/linkco/exa/Temporal_Memory_Graph/data/三体1疯狂年代.txt"
}