{
  "id": "cache_20260205_145900_e6750d4d",
  "physical_time": "2026-02-05T14:59:00.715527",
  "activity_type": "知识图谱整理-关系生成",
  "filename": "cache_20260205_145900_e6750d4d.md",
  "text": "实体1:\n- name: 太阳（巨月）\n- content: 巨月是乱纪元三体世界中的一个天体,围绕三体星系母星运行,并非传统意义上的月亮。它由三体文明行星被撕裂后剩余的一半构成,大小约为原行星的四分之一,是宇宙大撕裂的产物,也是三体文明历史上灾难性的象征。巨月在大多数时候不会升起,但在夜空中是重要的组成部分,监听员曾观察到乱纪元中荒凉的大地和黑夜中的巨月。它最初不发光,而是反射光线,表面曾呈现木纹状并经历过发热阶段,核心平原一度呈现红光,但现在已冷却,最终呈现出如同宇宙巨牛犄角般的银色光芒。巨月的引力变化极快且无常,对三体星系环境产生显著影响,例如影响单摆摆动周期:当巨月位于母星的一面时,引力减小;位于另一面时,引力叠加,反映了该星系的不稳定性。巨月表面残留着191号文明的废墟,目前是一个没有生命的星球,并在过去事件的回忆中扮演关键角色。\n- memory_cache: ## 记忆缓存 - 更新\n\n**1. 当前摘要**\n\n当前阅读的内容主要围绕着审讯叶文洁以及对截获的三体信息的进一步探讨展开。审讯者向叶文洁透露了“审判日”号指挥中心人员的死状——死者在临终前试图爬向一台电脑，而这台电脑中存储着被截留的三体信息。叶文洁对28G的信息量表示怀疑，认为星际通讯效率低下难以实现。审讯者回应称，实际情况远远超乎想象。随后，文本转向对三体世界监听站的描述，介绍了1379号监听站及其监听员的工作和生活状态。监听员身处乱纪元的三体世界，在恒温的监听室内度过孤寂的岁月，监听着宇宙中的电波，但大部分时间接收到的只是无意义的噪声。监听员透过窗户观察到乱纪元中荒凉的大地和黑夜。\n\n*   **行动推进：** 审讯继续，审讯者试图引导叶文洁了解三体信息。场景切换至三体世界的监听站，介绍了监听员的工作环境和状态。\n*   **环境描述：** 详细描绘了审讯室的氛围，以及乱纪元三体世界的荒凉景象和监听站的封闭环境。\n*   **人物心理：** 叶文洁对三体信息的真实性表示怀疑，监听员则表现出极度的孤寂和对宇宙的茫然。\n*   **细节描写：** 对“审判日”号指挥中心人员死状的描写，以及乱纪元中三体世界的景象描写，增强了场景的真实感和压抑感。\n*   **三体信息：** 28G的三体信息量仍然是一个谜团，其内容将对人类产生深远影响。\n*   **三体世界：** 乱纪元的三体世界呈现出一种荒凉、贫瘠的景象，暗示着三体文明所面临的困境。\n*   **监听员：** 监听员的职业和生活状态反映了三体文明对资源的限制和对宇宙探索的执着。\n*   **时间线：** 三体文明监听站已经存在上千年，暗示着其悠久的历史和对宇宙的长期关注。\n\n**2. 自我思考**\n\n*   **关注内容：**\n    *   三体信息的具体内容是什么？它将如何影响人类对三体文明的认知？\n    *   乱纪元的三体世界是什么样的？三体文明为何处于乱纪元？\n    *   监听员的职业和生活状态反映了三体文明的哪些特点？\n    *   监听站的作用是什么？它对三体文明的生存和发展起到了什么作用？\n    *   28G信息量如何传输，以及监听站接收到的无意义噪声是否隐藏着某种信息？\n*   **预判重点：**\n    *   三体信息将揭示三体文明的真实面貌，以及他们对人类的威胁。\n    *   乱纪元的三体世界将对理解三体文明的起源和发展提供线索。\n    *   监听员的经历将揭示三体文明的价值观和生存哲学。\n    *   监听站可能会在未来发挥关键作用，例如接收到来自人类的信息或发出警告。\n*   **疑虑/注意：**\n    *   审讯者对叶文洁的引导方式，暗示着他们可能已经掌握了某些关键信息，并试图利用叶文洁来解读三体信息。\n    *   乱纪元的三体世界与地球的文明社会形成鲜明对比，暗示着两种文明之间存在着巨大的差异。\n    *   监听员的孤寂和茫然，可能反映了三体文明对宇宙的绝望和对未来的不确定。\n\n**3. 系统状态**\n\n*   **文档名：** 三体1疯狂年代.txt\n*   **已处理文本范围：** 处理到“整条线就像是所有沙粒排成行形成的一维沙漠，荒”结束。\n\n实体2:\n- name: 大太阳（太阳）\n- content: 在“乱纪元”世界中存在一种巨大的蓝色太阳,其直径占据地平线至少五分之一。它亮度极高,能够提供温暖并照亮大地,但这种状态持续时间短暂。这种太阳运行规律无规律,与传统行星围绕恒星的周期性运动不同,这是“乱纪元”概念的核心特征。它会迅速释放出暖流和灼热的高温,导致大地融化、热浪滚滚,对生物构成严重威胁,即使遮挡也难以抵御其强光和高温。\n- memory_cache: ## 记忆缓存 - 更新\n\n**1. 当前摘要**\n\n汪淼从“浸泡”游戏中退出，发现自己被冷汗浸透，仿佛从一场噩梦中醒来。游戏结束时，金字塔被雪覆盖，雪层分层，从下至上分别是水的雪、干冰的雪和固态氧氮的雪。夜空中出现一行字，宣告第137号文明在持续四十八年的严寒中毁灭，但文明的种子将重新启动。汪淼最后看到的仍然是夜空中的三颗飞星，它们相互围绕，跳着诡异的舞蹈。\n\n随后，汪淼前往丁仪提供的地址，去杨冬的母亲家。在路上，他被“乱纪元”的概念所困扰，无法理解那个世界太阳运行的无规律性。他意识到《三体》的真实不在于精美的画面，而在于隐藏在深层的信息量。他回忆起大学课堂上教授的例子，空旷的天空中一缕白云所包含的信息量远大于《清明上河图》。汪淼意识到《三体》的设计者与传统游戏设计者反其道而行之，隐藏了大量信息。他开始意识到《三体》的特殊之处，并试图理解其深层含义。\n\n**2. 自我思考**\n\n*   **关注内容：**\n    *   “乱纪元”的含义是什么？它与三体世界的太阳运行规律有何联系？\n    *   《三体》的设计者为何要隐藏大量信息？他们试图传递什么信息？\n    *   三颗飞星在游戏结束时的出现，以及它们诡异的舞蹈，是否预示着未来的发展？\n    *   汪淼对“乱纪元”的执着，以及他试图理解《三体》深层含义的行为，预示着他将成为解开谜团的关键人物。\n    *   杨冬的母亲可能掌握着关于《三体》的重要信息，汪淼的拜访可能会揭示新的线索。\n*   **预判重点：**\n    *   “乱纪元”可能与三体世界的生存环境或历史有关，它可能是某种关键的线索。\n    *   《三体》的设计者可能试图通过隐藏信息来引导玩家思考，或者传递某种警告。\n    *   三颗飞星可能与三体世界的某种力量或文明有关，它们可能是某种宇宙信号或警告。\n    *   杨冬的母亲可能会揭示关于《三体》的更多信息，例如游戏的起源、目的或设计者。\n*   **疑虑/注意：**\n    *   汪淼对“乱纪元”的执着，以及他试图理解《三体》深层含义的行为，可能会让他陷入危险。\n    *   《三体》的设计者可能隐藏着某些秘密，他们可能并非善意。\n    *   三颗飞星的出现，以及它们诡异的舞蹈，暗示着未来的发展可能充满危机。\n\n**3. 系统状态**\n\n*   **文档名：** 三体1疯狂年代.txt\n*   **已处理文本范围：** 处理到“《三体》的设计者是反其道而行之”结束。\n",
  "document_path": ""
}